qkeras/__init__.py
qkeras/b2t.py
qkeras/bn_folding_utils.py
qkeras/callbacks.py
qkeras/codebook.py
qkeras/estimate.py
qkeras/qconv2d_batchnorm.py
qkeras/qconvolutional.py
qkeras/qdepthwiseconv2d_batchnorm.py
qkeras/qlayers.py
qkeras/qnormalization.py
qkeras/qoctave.py
qkeras/qpooling.py
qkeras/qrecurrent.py
qkeras/quantizers.py
qkeras/safe_eval.py
qkeras/utils.py
qkeras/autoqkeras/__init__.py
qkeras/autoqkeras/autoqkeras_internal.py
qkeras/autoqkeras/quantization_config.py
qkeras/autoqkeras/utils.py
qkeras/autoqkeras/forgiving_metrics/__init__.py
qkeras/autoqkeras/forgiving_metrics/forgiving_bits.py
qkeras/autoqkeras/forgiving_metrics/forgiving_energy.py
qkeras/autoqkeras/forgiving_metrics/forgiving_factor.py
qkeras/qtools/__init__.py
qkeras/qtools/config_public.py
qkeras/qtools/generate_layer_data_type_map.py
qkeras/qtools/interface.py
qkeras/qtools/qgraph.py
qkeras/qtools/qtools_util.py
qkeras/qtools/run_qtools.py
qkeras/qtools/settings.py
qkeras/qtools/qenergy/__init__.py
qkeras/qtools/qenergy/qenergy.py
qkeras/qtools/quantized_operators/__init__.py
qkeras/qtools/quantized_operators/accumulator_factory.py
qkeras/qtools/quantized_operators/accumulator_impl.py
qkeras/qtools/quantized_operators/adder_factory.py
qkeras/qtools/quantized_operators/adder_impl.py
qkeras/qtools/quantized_operators/divider_factory.py
qkeras/qtools/quantized_operators/divider_impl.py
qkeras/qtools/quantized_operators/merge_factory.py
qkeras/qtools/quantized_operators/multiplier_factory.py
qkeras/qtools/quantized_operators/multiplier_impl.py
qkeras/qtools/quantized_operators/qbn_factory.py
qkeras/qtools/quantized_operators/quantizer_factory.py
qkeras/qtools/quantized_operators/quantizer_impl.py
qkeras/qtools/quantized_operators/subtractor_factory.py
QKeras-0.9.0.dist-info/LICENSE
QKeras-0.9.0.dist-info/METADATA
QKeras-0.9.0.dist-info/WHEEL
QKeras-0.9.0.dist-info/top_level.txt
QKeras-0.9.0.dist-info/RECORD
