Metadata-Version: 2.1
Name: QKeras
Version: 0.9.0
Summary: Quantization package for Keras
Home-page: https://github.com/google/qkeras
Author: QKeras Team
Author-email: qkeras-team@google.com
Maintainer: Hao Zhuang
Maintainer-email: hzhuang@google.com
License: Apache v.2.0
Platform: UNKNOWN
Classifier: Programming Language :: Python :: 3
Classifier: License :: OSI Approved :: Apache Software License
Classifier: Operating System :: OS Independent
Requires-Python: >=3.7
License-File: LICENSE
Requires-Dist: numpy (>=1.16.0)
Requires-Dist: scipy (>=1.4.1)
Requires-Dist: pyparser
Requires-Dist: setuptools (>=41.0.0)
Requires-Dist: tensorflow-model-optimization (>=0.2.1)
Requires-Dist: networkx (>=2.1)
Requires-Dist: keras-tuner (>=1.0.1)
Requires-Dist: scikit-learn (>=0.23.1)
Requires-Dist: tqdm (>=4.48.0)
